{
  "locks": {
    "francia5ge": {
      "device_id": "DEV_641879e91b1bdaecd605",
      "api_hash_hash": "2bfd52d01e94c2adb63ae9fb4c0ecd433240a0c824889109ce218ae853e1663f",
      "date_liaison": "2026-07-14 12:52:10",
      "statut": "verrouille"
    },
    "facielgfey": {
      "device_id": "DEV_11e2832a98a71bed66dc",
      "api_hash_hash": "692392105ddcb186f54bcb28efb5e44f67b5f8bcb8b3054c6d296f92080022a6",
      "date_liaison": "2026-07-14 13:22:35",
      "statut": "verrouille"
    },
    "Sedillontdfg": {
      "device_id": "DEV_2a1e5a4885927890d547",
      "api_hash_hash": "7d7b1b93c497d07436896384832605bf3731b0710c33e1eb3022647c85b69eeb",
      "date_liaison": "2026-07-14 13:41:36",
      "statut": "verrouille"
    },
    "alexdetdi": {
      "device_id": "DEV_e45265850915a3dd98f4",
      "api_hash_hash": "8f71a9784c7b04e2b8cc2d8ed6489204c9424bc0b6f0f9bde669adfc7a425a80",
      "date_liaison": "2026-07-14 14:03:40",
      "statut": "verrouille"
    },
    "valerio99tp": {
      "device_id": "DEV_f0d526d7cf94388171fa",
      "api_hash_hash": "f034cf15333baaf1c5ccf61c6016faafe6dddfc5abd67de14057eca10e0c8b1a",
      "date_liaison": "2026-07-14 16:03:47",
      "statut": "verrouille"
    },
    "honlio6in71": {
      "device_id": "DEV_a1212fa1955261947a85",
      "api_hash_hash": "6227a4d4bb45305324abc2406748305e14a1da980098fb912719a790a5b704a7",
      "date_liaison": "2026-07-14 16:28:41",
      "statut": "verrouille"
    },
    "nainauwwdr": {
      "device_id": "DEV_e48928e7ecad3427c269",
      "api_hash_hash": "eaa81221df41c301dbe5bf14cd68f0708bf9894f49c49efbea3c59b640a11ce6",
      "date_liaison": "2026-07-14 17:05:11",
      "statut": "verrouille"
    },
    "babasephilbert": {
      "device_id": "DEV_4c4407828e101ecf8a6e",
      "api_hash_hash": "5818df4dc7cdfdd376d23ee495815406e6b5a10ca99b5e2428fdd53a0a07caa7",
      "date_liaison": "2026-07-14 17:20:37",
      "statut": "verrouille"
    },
    "esly3drhf": {
      "device_id": "DEV_867480973ac561981ea9",
      "api_hash_hash": "6835a82b29f05b5f38af49f0887ce2d5db72638cd9092ae1b41723b0b585f054",
      "date_liaison": "2026-07-14 17:39:43",
      "statut": "verrouille"
    },
    "mioratoudgev": {
      "device_id": "DEV_ef2bc694d475c1e925fd",
      "api_hash_hash": "3faae18aac1e3e45ddf56e816bd97cbfe620f99911188f27081a8c1b3bfd8dbd",
      "date_liaison": "2026-07-14 17:44:56",
      "statut": "verrouille"
    },
    "boydah": {
      "device_id": "DEV_52c9ff0afc440aab92a2",
      "api_hash_hash": "9fea4702feacfdecbb0a8d455b18987c455936b9530566d1c26c0762aca609b0",
      "date_liaison": "2026-07-14 17:53:35",
      "statut": "verrouille"
    },
    "loyaledrt": {
      "device_id": "DEV_5264730ec78a96fd9bd4",
      "api_hash_hash": "7e61c73f92d1e46e81cacff4c5d6ce47f3e3ff04cecd1e3bae6bc8628191c985",
      "date_liaison": "2026-07-14 17:55:00",
      "statut": "verrouille"
    },
    "sitrakpaup5": {
      "device_id": "DEV_2c19b8d22299ed546f94",
      "api_hash_hash": "e0d2eddf6cb96ca305774f8dab62c34d84278bb1931f32cafe37035bcc102c05",
      "date_liaison": "2026-07-14 18:29:25",
      "statut": "verrouille"
    }
  }
}