{
  "locks": {
    "powelluydf2": {
      "device_id": "DEV_d8818e3512ec9554e4b8",
      "api_hash_hash": "9e461e3c1c01847c103a886849c26c17e43fb0084db0722e4f2b060697824e98",
      "date_liaison": "2026-06-15 21:50:49",
      "statut": "verrouille"
    },
    "boydah": {
      "device_id": "DEV_52c9ff0afc440aab92a2",
      "api_hash_hash": "9fea4702feacfdecbb0a8d455b18987c455936b9530566d1c26c0762aca609b0",
      "date_liaison": "2026-06-15 22:04:07",
      "statut": "verrouille"
    },
    "trixpooej": {
      "device_id": "DEV_47433b4d7f47b9fdef12",
      "api_hash_hash": "a7246cd5ceb2f67c7a7ad741441f15149936e7f50694dbb238b496002fbcc193",
      "date_liaison": "2026-06-15 22:07:51",
      "statut": "verrouille"
    },
    "anniciahe": {
      "device_id": "DEV_2f65b5cfc5f179c9f0e9",
      "api_hash_hash": "c41bef8ff509db28efb0f71891a7dd4ad83ddf9526f33aeba0e29e41eb80c7dc",
      "date_liaison": "2026-06-15 22:10:57",
      "statut": "verrouille"
    }
  }
}