{
  "locks": {
    "adreafhrt": {
      "device_id": "DEV_3dfdb53e2cf6df7bf8d5",
      "api_hash_hash": "9ec31116f21b418e4c5857d0cbc6ac79ab306d4b882a48aabb045161d72cebcc",
      "date_liaison": "2026-06-02 19:37:05",
      "statut": "verrouille"
    },
    "alexdetdi": {
      "device_id": "DEV_e45265850915a3dd98f4",
      "api_hash_hash": "8f71a9784c7b04e2b8cc2d8ed6489204c9424bc0b6f0f9bde669adfc7a425a80",
      "date_liaison": "2026-06-02 19:46:41",
      "statut": "verrouille"
    },
    "loyaledrt": {
      "device_id": "DEV_5264730ec78a96fd9bd4",
      "api_hash_hash": "7e61c73f92d1e46e81cacff4c5d6ce47f3e3ff04cecd1e3bae6bc8628191c985",
      "date_liaison": "2026-06-02 19:51:59",
      "statut": "verrouille"
    },
    "moiadmin": {
      "device_id": "DEV_601e8f44c08a02895fb9",
      "api_hash_hash": "8cec64e7709c8df7a91973625f12412d82ba2b0165e091eaa76225b22b0467b4",
      "date_liaison": "2026-06-02 20:00:16",
      "statut": "verrouille"
    },
    "miorahdkdl": {
      "device_id": "DEV_3f3800712a64d7ef6acc",
      "api_hash_hash": "aff5dc418ea412e5114263899259d6ef661fa24704a3d20a7ee423ba7abf33e9",
      "date_liaison": "2026-06-02 20:14:08",
      "statut": "verrouille"
    }
  }
}